domain/__init__.py
domain/alias.py
domain/certificate_management.py
domain/contact.py
domain/equipment_management.py
domain/label.py
domain/script_model.py
domain/site.py
domain/switch_management.py
domain/to.py
output/__init__.py
output/alias_dns.py
output/certificate_shell.py
output/contact_database.py
output/contact_sheet.py
output/database_base.py
output/equipment_shell.py
output/label_database.py
output/script_model_shell.py
output/site_database.py
output/switch_shell.py
aleoso-0.0.7.dist-info/METADATA
aleoso-0.0.7.dist-info/WHEEL
aleoso-0.0.7.dist-info/top_level.txt
aleoso-0.0.7.dist-info/RECORD
