Metadata-Version: 2.1
Name: aleoso
Version: 0.0.7
Summary: Lib
Author: Aleos
Author-email: aae5654ae@mozmail.com
License: MIT
Classifier: Programming Language :: Python :: 3
Classifier: License :: OSI Approved :: MIT License
Classifier: Operating System :: OS Independent
Requires-Dist: fastapi
Requires-Dist: fabric
Requires-Dist: uvicorn
Requires-Dist: pandas
Requires-Dist: openpyxl
Requires-Dist: starlette
Requires-Dist: schedule
Requires-Dist: SQLAlchemy
Requires-Dist: ldap3
